pylambdarest/__init__.py
pylambdarest/request.py
pylambdarest/route.py
pylambdarest-0.2.1.dist-info/LICENSE
pylambdarest-0.2.1.dist-info/WHEEL
pylambdarest-0.2.1.dist-info/METADATA
pylambdarest-0.2.1.dist-info/RECORD
