Metadata-Version: 2.1
Name: pylambdarest
Version: 0.2.1
Summary: Lightweight framework for building REST API using AWS Lambda + API Gateway
Home-page: https://github.com/MarwanDebbiche/pylambdarest
License: MIT
Keywords: aws-lambda,serverless,api-gateway,rest-api
Author: Marwan Debbiche (Macbook Pro)
Author-email: marwan.debbiche@gmail.com
Requires-Python: >=3.7.2,<4.0.0
Classifier: License :: OSI Approved :: MIT License
Classifier: Operating System :: OS Independent
Classifier: Programming Language :: Python :: 3
Classifier: Programming Language :: Python :: 3.10
Classifier: Programming Language :: Python :: 3.8
Classifier: Programming Language :: Python :: 3.9
Requires-Dist: PyJWT (>=2.6.0,<3.0.0)
Requires-Dist: jsonschema (>=3.2.0,<4.0.0)
Requires-Dist: simplejson (>=3.17.2,<4.0.0)
Project-URL: Documentation, https://pylambdarest.readthedocs.io
Project-URL: Repository, https://github.com/MarwanDebbiche/pylambdarest
